bancorml/__init__.py
bancorml/main.py
bancorml/agents/__init__.py
bancorml/agents/agent_base.py
bancorml/agents/liquidity_provider_agent.py
bancorml/agents/random_walk.py
bancorml/agents/trader_agent.py
bancorml/environments/__init__.py
bancorml/environments/bancor3.py
bancorml/environments/env_base.py
bancorml/environments/observation_space.py
bancorml/environments/tokenomics/__init__.py
bancorml/environments/tokenomics/fixed_point_tokenomics.py
bancorml/environments/tokenomics/floating_point_tokenomics.py
bancorml/environments/tokenomics/tokenomics_base.py
bancorml/environments/tokenomics/ledgers/__init__.py
bancorml/environments/tokenomics/ledgers/available_liquidity_ledger.py
bancorml/environments/tokenomics/ledgers/external_wallet_ledger.py
bancorml/environments/tokenomics/ledgers/ledger_base.py
bancorml/environments/tokenomics/ledgers/pool_token_supply_ledger.py
bancorml/environments/tokenomics/ledgers/staking_ledger.py
bancorml/environments/tokenomics/ledgers/vault_ledger.py
bancorml/environments/tokenomics/ledgers/vortex_ledger.py
bancorml/tests/__init__.py
bancorml/tests/conftest.py
bancorml/tests/environment_tests/__init__.py
bancorml/tests/environment_tests/test_environments.py
bancorml/tests/environment_tests/data/withdrawal_algorithm_tests.json
bancorml/utils/__init__.py
bancorml/utils/cli_utils.py
bancorml/utils/crypto_utils.py
bancorml/utils/data_utils.py
bancorml/utils/logger.py
bancorml/utils/schemas.py
bancorml-0.2.38.data/data/bancorml/tests/data/withdrawal_algorithm_tests.json
bancorml-0.2.38.dist-info/LICENSE
bancorml-0.2.38.dist-info/METADATA
bancorml-0.2.38.dist-info/WHEEL
bancorml-0.2.38.dist-info/entry_points.txt
bancorml-0.2.38.dist-info/top_level.txt
bancorml-0.2.38.dist-info/RECORD
