Metadata-Version: 2.1
Name: bancorml
Version: 0.2.38
Summary: BancorML is a library that builds, optimizes, and evaluates machine learning pipelines in the context of a multi-agent system
Home-page: https://github.com/gcode-ai/bancorml
Author: Bancor Network
Author-email: mike@bancor.network
License: UNKNOWN
Platform: UNKNOWN
License-File: LICENSE
Requires-Dist: pandas
Requires-Dist: numpy
Requires-Dist: pydantic
Requires-Dist: fxpmath
Requires-Dist: matplotlib
Provides-Extra: complete
